report/__init__.py
report/__main__.py
report/plugin.py
report/workflow/__init__.py
report/workflow/build.py
report/workflow/confluence.py
report/workflow/html.py
report/workflow/settings.py
report/workflow/xml.py
pytest_confluence_report-0.0.4.dist-info/AUTHORS.md
pytest_confluence_report-0.0.4.dist-info/LICENSE.md
pytest_confluence_report-0.0.4.dist-info/METADATA
pytest_confluence_report-0.0.4.dist-info/WHEEL
pytest_confluence_report-0.0.4.dist-info/entry_points.txt
pytest_confluence_report-0.0.4.dist-info/top_level.txt
pytest_confluence_report-0.0.4.dist-info/RECORD
