Metadata-Version: 2.1
Name: pytest-confluence-report
Version: 0.0.4
Summary: Package stands for pytest plugin to upload results into Confluence page.
Home-page: https://github.com/vyahello/pytest-confluence-report
Author: Volodymyr Yahello
Author-email: vyahello@gmail.com
License: UNKNOWN
Platform: UNKNOWN
Classifier: Framework :: Pytest
Classifier: Topic :: Software Development :: Testing
Classifier: Programming Language :: Python :: 3.6
Classifier: Programming Language :: Python :: 3.7
Classifier: Programming Language :: Python :: 3.8
Classifier: Programming Language :: Python :: 3.9
Classifier: License :: OSI Approved :: MIT License
Classifier: Operating System :: OS Independent
Requires-Python: >=3.6
License-File: LICENSE.md
License-File: AUTHORS.md
Requires-Dist: attrs (==19.3.0)
Requires-Dist: atlassian-python-api (==1.17.5)
Requires-Dist: junitparser (==1.4.1)
Requires-Dist: loguru (==0.5.3)
Requires-Dist: lxml (==4.5.2)
Requires-Dist: typed-ast (==1.5.2)
Requires-Dist: typer (==0.3.2)
Requires-Dist: uyaml (==0.0.7)
